rag/__init__.py
rag/config.py
rag/model.py
rag/chunking/__init__.py
rag/chunking/base_chunker.py
rag/chunking/line_chunker.py
rag/db/__init__.py
rag/db/db_file_handler.py
rag/db/dimension_utils.py
rag/db/models.py
rag/embeddings/__init__.py
rag/embeddings/base.py
rag/embeddings/mock_embedder.py
rag/embeddings/openai_embedder.py
postgres_rag-0.1.0.dist-info/LICENSE
postgres_rag-0.1.0.dist-info/METADATA
postgres_rag-0.1.0.dist-info/WHEEL
postgres_rag-0.1.0.dist-info/top_level.txt
postgres_rag-0.1.0.dist-info/RECORD
