Metadata-Version: 2.2
Name: postgres-rag
Version: 0.1.0
Summary: RAG (Retrieval-Augmented Generation) System
Home-page: https://github.com/RichardHightower/rag
Author: Richard Hightower
Author-email: richardhightower@gmail.com
Classifier: Development Status :: 3 - Alpha
Classifier: Intended Audience :: Developers
Classifier: License :: OSI Approved :: MIT License
Classifier: Programming Language :: Python :: 3.12
Requires-Python: >=3.12,<3.13
License-File: LICENSE
Requires-Dist: openai<2.0.0,>=1.58.1
Requires-Dist: sqlalchemy<3.0.0,>=2.0.36
Requires-Dist: psycopg2-binary<3.0.0,>=2.9.10
Requires-Dist: pgvector<0.4.0,>=0.3.6
Requires-Dist: python-dotenv<2.0.0,>=1.0.1
Provides-Extra: dev
Requires-Dist: black<25.0.0,>=24.1.0; extra == "dev"
Requires-Dist: isort<6.0.0,>=5.13.0; extra == "dev"
Requires-Dist: mypy<2.0.0,>=1.8.0; extra == "dev"
Requires-Dist: pytest<9.0.0,>=8.0.0; extra == "dev"
Requires-Dist: pytest-cov<5.0.0,>=4.1.0; extra == "dev"
Requires-Dist: types-psycopg2<3.0.0,>=2.9.21; extra == "dev"
Dynamic: author
Dynamic: author-email
Dynamic: classifier
Dynamic: description
Dynamic: description-content-type
Dynamic: home-page
Dynamic: provides-extra
Dynamic: requires-dist
Dynamic: requires-python
Dynamic: summary
